{
"meta":{"test_sets":[],"test_metrics":[],"learn_metrics":[{"best_value":"Min","name":"RMSE"}],"launch_mode":"Train","parameters":"","iteration_count":100,"learn_sets":["learn"],"name":"experiment"},
"iterations":[
{"learn":[14.00293704],"iteration":0,"passed_time":0.0007812101425,"remaining_time":0.0773398041},
{"learn":[13.10075263],"iteration":1,"passed_time":0.001402391494,"remaining_time":0.06871718322},
{"learn":[12.27580639],"iteration":2,"passed_time":0.002001755416,"remaining_time":0.06472342511},
{"learn":[11.53096249],"iteration":3,"passed_time":0.002571092801,"remaining_time":0.06170622722},
{"learn":[10.830431],"iteration":4,"passed_time":0.003145429379,"remaining_time":0.05976315821},
{"learn":[10.25706321],"iteration":5,"passed_time":0.003692777089,"remaining_time":0.05785350772},
{"learn":[9.746114746],"iteration":6,"passed_time":0.004303124239,"remaining_time":0.05717007918},
{"learn":[9.293929443],"iteration":7,"passed_time":0.004864286716,"remaining_time":0.05593929723},
{"learn":[8.88766779],"iteration":8,"passed_time":0.005446187344,"remaining_time":0.05506700536},
{"learn":[8.480572438],"iteration":9,"passed_time":0.006025042461,"remaining_time":0.05422538214},
{"learn":[8.124657378],"iteration":10,"passed_time":0.006572731209,"remaining_time":0.05317937069},
{"learn":[7.834424261],"iteration":11,"passed_time":0.007132601061,"remaining_time":0.05230574112},
{"learn":[7.590564829],"iteration":12,"passed_time":0.007688131523,"remaining_time":0.05145134173},
{"learn":[7.361250937],"iteration":13,"passed_time":0.008394461687,"remaining_time":0.05156597893},
{"learn":[7.12082075],"iteration":14,"passed_time":0.008952154471,"remaining_time":0.05072887533},
{"learn":[6.889449618],"iteration":15,"passed_time":0.009486351609,"remaining_time":0.04980334595},
{"learn":[6.704827343],"iteration":16,"passed_time":0.0100493978,"remaining_time":0.04906470692},
{"learn":[6.555478184],"iteration":17,"passed_time":0.01059971792,"remaining_time":0.04828760386},
{"learn":[6.405085744],"iteration":18,"passed_time":0.01116314814,"remaining_time":0.04759026311},
{"learn":[6.27284254],"iteration":19,"passed_time":0.01173658333,"remaining_time":0.04694633332},
{"learn":[6.153017304],"iteration":20,"passed_time":0.01230094066,"remaining_time":0.04627496724},
{"learn":[6.062929035],"iteration":21,"passed_time":0.01296224325,"remaining_time":0.04595704427},
{"learn":[5.968388598],"iteration":22,"passed_time":0.01355527269,"remaining_time":0.04538069552},
{"learn":[5.876809566],"iteration":23,"passed_time":0.01412955279,"remaining_time":0.04474358385},
{"learn":[5.793944187],"iteration":24,"passed_time":0.01469932911,"remaining_time":0.04409798732},
{"learn":[5.739477903],"iteration":25,"passed_time":0.01528845714,"remaining_time":0.04351330108},
{"learn":[5.672850979],"iteration":26,"passed_time":0.01585231906,"remaining_time":0.04285997377},
{"learn":[5.631069772],"iteration":27,"passed_time":0.01642158774,"remaining_time":0.0422269399},
{"learn":[5.584502358],"iteration":28,"passed_time":0.01700772767,"remaining_time":0.04163960913},
{"learn":[5.540229032],"iteration":29,"passed_time":0.0175723156,"remaining_time":0.04100206974},
{"learn":[5.493938932],"iteration":30,"passed_time":0.01813977555,"remaining_time":0.04037562944},
{"learn":[5.461156489],"iteration":31,"passed_time":0.01872630892,"remaining_time":0.03979340645},
{"learn":[5.420940209],"iteration":32,"passed_time":0.01931112109,"remaining_time":0.03920742766},
{"learn":[5.391537275],"iteration":33,"passed_time":0.01988780792,"remaining_time":0.03860574478},
{"learn":[5.362664869],"iteration":34,"passed_time":0.02050052666,"remaining_time":0.03807240665},
{"learn":[5.336743106],"iteration":35,"passed_time":0.02107424077,"remaining_time":0.03746531693},
{"learn":[5.316418384],"iteration":36,"passed_time":0.02164110931,"remaining_time":0.0368483753},
{"learn":[5.287401002],"iteration":37,"passed_time":0.02222758432,"remaining_time":0.03626605862},
{"learn":[5.26933335],"iteration":38,"passed_time":0.02286529934,"remaining_time":0.03576367333},
{"learn":[5.246349502],"iteration":39,"passed_time":0.02342977683,"remaining_time":0.03514466525},
{"learn":[5.226009373],"iteration":40,"passed_time":0.02401177911,"remaining_time":0.0345535358},
{"learn":[5.212602214],"iteration":41,"passed_time":0.0245810092,"remaining_time":0.03394520318},
{"learn":[5.195333424],"iteration":42,"passed_time":0.02515632654,"remaining_time":0.03334675844},
{"learn":[5.180058965],"iteration":43,"passed_time":0.02573807312,"remaining_time":0.03275754761},
{"learn":[5.167002285],"iteration":44,"passed_time":0.02629887824,"remaining_time":0.03214307341},
{"learn":[5.147248088],"iteration":45,"passed_time":0.02685681041,"remaining_time":0.03152756005},
{"learn":[5.123481198],"iteration":46,"passed_time":0.02745420151,"remaining_time":0.0309589932},
{"learn":[5.109888346],"iteration":47,"passed_time":0.0280367403,"remaining_time":0.03037313532},
{"learn":[5.093005619],"iteration":48,"passed_time":0.02860439413,"remaining_time":0.02977192042},
{"learn":[5.077633544],"iteration":49,"passed_time":0.02917615644,"remaining_time":0.02917615644},
{"learn":[5.064204419],"iteration":50,"passed_time":0.0297484631,"remaining_time":0.0285818567},
{"learn":[5.04754041],"iteration":51,"passed_time":0.03029644269,"remaining_time":0.0279659471},
{"learn":[5.036041667],"iteration":52,"passed_time":0.0308670112,"remaining_time":0.02737263258},
{"learn":[5.013674427],"iteration":53,"passed_time":0.03144846286,"remaining_time":0.02678943133},
{"learn":[5.001897547],"iteration":54,"passed_time":0.0320181598,"remaining_time":0.0261966762},
{"learn":[4.99468815],"iteration":55,"passed_time":0.0325750243,"remaining_time":0.02559466195},
{"learn":[4.979703478],"iteration":56,"passed_time":0.0331712009,"remaining_time":0.0250238884},
{"learn":[4.953716627],"iteration":57,"passed_time":0.03375090877,"remaining_time":0.02444031325},
{"learn":[4.940505105],"iteration":58,"passed_time":0.03432006607,"remaining_time":0.02384953744},
{"learn":[4.935868258],"iteration":59,"passed_time":0.03492146211,"remaining_time":0.02328097474},
{"learn":[4.927856863],"iteration":60,"passed_time":0.03548070416,"remaining_time":0.02268438462},
{"learn":[4.922291031],"iteration":61,"passed_time":0.03614943024,"remaining_time":0.02215610241},
{"learn":[4.912818304],"iteration":62,"passed_time":0.03673578039,"remaining_time":0.02157498213},
{"learn":[4.895115666],"iteration":63,"passed_time":0.03731290458,"remaining_time":0.02098850883},
{"learn":[4.887597293],"iteration":64,"passed_time":0.03790038859,"remaining_time":0.02040790155},
{"learn":[4.878429565],"iteration":65,"passed_time":0.03848314135,"remaining_time":0.01982464857},
{"learn":[4.87387694],"iteration":66,"passed_time":0.03903805091,"remaining_time":0.01922769672},
{"learn":[4.864015931],"iteration":67,"passed_time":0.03960180617,"remaining_time":0.01863614408},
{"learn":[4.858831256],"iteration":68,"passed_time":0.04015912936,"remaining_time":0.01804250739},
{"learn":[4.843490624],"iteration":69,"passed_time":0.04073510086,"remaining_time":0.01745790037},
{"learn":[4.83189978],"iteration":70,"passed_time":0.04129790798,"remaining_time":0.0168681596},
{"learn":[4.823242775],"iteration":71,"passed_time":0.04185504167,"remaining_time":0.01627696065},
{"learn":[4.812634448],"iteration":72,"passed_time":0.04243757355,"remaining_time":0.01569608885},
{"learn":[4.79964049],"iteration":73,"passed_time":0.04301652185,"remaining_time":0.01511391308},
{"learn":[4.792394728],"iteration":74,"passed_time":0.04357095578,"remaining_time":0.01452365193},
{"learn":[4.782643831],"iteration":75,"passed_time":0.04414614417,"remaining_time":0.01394088763},
{"learn":[4.772178557],"iteration":76,"passed_time":0.044691584,"remaining_time":0.01334943418},
{"learn":[4.764106895],"iteration":77,"passed_time":0.04524075519,"remaining_time":0.012760213},
{"learn":[4.756644453],"iteration":78,"passed_time":0.04579598352,"remaining_time":0.01217361587},
{"learn":[4.750886727],"iteration":79,"passed_time":0.04634223814,"remaining_time":0.01158555954},
{"learn":[4.746633109],"iteration":80,"passed_time":0.04689045461,"remaining_time":0.01099899553},
{"learn":[4.736623517],"iteration":81,"passed_time":0.04746671977,"remaining_time":0.01041952385},
{"learn":[4.727455327],"iteration":82,"passed_time":0.04803790103,"remaining_time":0.009839088162},
{"learn":[4.713909486],"iteration":83,"passed_time":0.04861005364,"remaining_time":0.009259057835},
{"learn":[4.694000833],"iteration":84,"passed_time":0.04917065984,"remaining_time":0.008677175267},
{"learn":[4.684361587],"iteration":85,"passed_time":0.04974331946,"remaining_time":0.00809774968},
{"learn":[4.680203256],"iteration":86,"passed_time":0.05049738543,"remaining_time":0.007545586329},
{"learn":[4.660692133],"iteration":87,"passed_time":0.05109768651,"remaining_time":0.006967866342},
{"learn":[4.642518214],"iteration":88,"passed_time":0.05167749603,"remaining_time":0.006387106251},
{"learn":[4.636848421],"iteration":89,"passed_time":0.05224240022,"remaining_time":0.005804711135},
{"learn":[4.628594094],"iteration":90,"passed_time":0.0528124476,"remaining_time":0.005223209104},
{"learn":[4.618976376],"iteration":91,"passed_time":0.05338179911,"remaining_time":0.004641895575},
{"learn":[4.612316611],"iteration":92,"passed_time":0.0539434209,"remaining_time":0.004060257487},
{"learn":[4.603867411],"iteration":93,"passed_time":0.05451774619,"remaining_time":0.00347985614},
{"learn":[4.598272187],"iteration":94,"passed_time":0.05508541948,"remaining_time":0.002899232604},
{"learn":[4.595268559],"iteration":95,"passed_time":0.05563887421,"remaining_time":0.002318286425},
{"learn":[4.587207776],"iteration":96,"passed_time":0.05621624626,"remaining_time":0.001738646791},
{"learn":[4.568880964],"iteration":97,"passed_time":0.05680373058,"remaining_time":0.001159259808},
{"learn":[4.558358667],"iteration":98,"passed_time":0.05737727935,"remaining_time":0.0005795684783},
{"learn":[4.552453273],"iteration":99,"passed_time":0.05796109193,"remaining_time":0}
]}